syntactic_tagger/__init__.py
syntactic_tagger/syntactic_tagger.py
syntactic_tagger/data_files/form_count.msgpack
syntactic_tagger/data_files/form_count.msgpack.bz2
syntactic_tagger/data_files/lexicon.msgpack
syntactic_tagger/data_files/lexicon.msgpack.bz2
syntactic_tagger/data_files/prefixes.msgpack
syntactic_tagger/data_files/prefixes.msgpack.bz2
syntactic_tagger/data_files/syntactic_table0.msgpack
syntactic_tagger/data_files/syntactic_table0.msgpack.bz2
syntactic_tagger/data_files/syntactic_table1.msgpack
syntactic_tagger/data_files/syntactic_table1.msgpack.bz2
syntactic_tagger/data_files/syntactic_table2.msgpack
syntactic_tagger/data_files/syntactic_table2.msgpack.bz2
syntactic_tagger/data_files/syntactic_table3.msgpack
syntactic_tagger/data_files/syntactic_table3.msgpack.bz2
syntactic_tagger/data_files/syntactic_table4.msgpack
syntactic_tagger/data_files/syntactic_table4.msgpack.bz2
syntactic_tagger/data_files/syntactic_table5.msgpack
syntactic_tagger/data_files/syntactic_table5.msgpack.bz2
syntactic_tagger/data_files/tag_number_converter.msgpack
syntactic_tagger/data_files/tag_number_converter.msgpack.bz2
syntactic_tagger-1.0.15.dist-info/METADATA
syntactic_tagger-1.0.15.dist-info/WHEEL
syntactic_tagger-1.0.15.dist-info/top_level.txt
syntactic_tagger-1.0.15.dist-info/RECORD
