Metadata-Version: 2.1
Name: syntactic-tagger
Version: 1.0.15
Summary: Spanish part-of-speech tagger using a syntactic table.
Home-page: https://pypi.org/project/syntactic-tagger/
Author: Ivan Arias Rodriguez
Author-email: ivan.arias.rodriguez@gmail.com
License: Creative Commons Attribution-NonCommercial-ShareAlike 4.0 International License
Platform: UNKNOWN
Classifier: Programming Language :: Python
Classifier: Development Status :: 1 - Planning
Classifier: Intended Audience :: Science/Research
Classifier: License :: Other/Proprietary License
Classifier: Natural Language :: Spanish
Classifier: Operating System :: OS Independent
Classifier: Programming Language :: Python :: 3 :: Only
Classifier: Topic :: Scientific/Engineering
Requires-Dist: msgpacku
Requires-Dist: iar-tokenizer
